pypmca/Adder.py
pypmca/Chain.py
pypmca/Collector.py
pypmca/Connector.py
pypmca/Delay.py
pypmca/Ensemble.py
pypmca/Injector.py
pypmca/Model.py
pypmca/Modifier.py
pypmca/Multiplier.py
pypmca/Operator.py
pypmca/Parameter.py
pypmca/Population.py
pypmca/Propagator.py
pypmca/Splitter.py
pypmca/Subtractor.py
pypmca/Transition.py
pypmca/__init__.py
pypmca/_version.py
pypmca/analysis/Optimizer.py
pypmca/analysis/Trajectory.py
pypmca/analysis/__init__.py
pypmca/tests/__init__.py
pypmca/tests/test_classes.py
pypmca/tests/test_properties.py
pypmca/tools/AgeModeller.py
pypmca/tools/Forecast_hub.py
pypmca/tools/Forecast_hub_de.py
pypmca/tools/Forecast_hub_eu.py
pypmca/tools/IntervalMaker.py
pypmca/tools/Scenario_hub.py
pypmca/tools/__init__.py
pypmca/tools/table.py
pypmca-0.3.3.dist-info/AUTHORS.rst
pypmca-0.3.3.dist-info/LICENSE
pypmca-0.3.3.dist-info/METADATA
pypmca-0.3.3.dist-info/WHEEL
pypmca-0.3.3.dist-info/top_level.txt
pypmca-0.3.3.dist-info/RECORD
