Metadata-Version: 2.1
Name: pypmca
Version: 0.3.3
Summary: pyPM.ca population modeller
Home-page: http://www.pypm.ca
Author: Dean Karlen
Author-email: karlen@uvic.ca
License: GNU General Public License v3
Keywords: pypmca
Platform: UNKNOWN
Classifier: Development Status :: 4 - Beta
Classifier: Intended Audience :: End Users/Desktop
Classifier: License :: OSI Approved :: GNU General Public License v3 (GPLv3)
Classifier: Natural Language :: English
Classifier: Programming Language :: Python :: 3
Classifier: Programming Language :: Python :: 3.5
Classifier: Programming Language :: Python :: 3.6
Classifier: Programming Language :: Python :: 3.7
Classifier: Programming Language :: Python :: 3.8
Requires-Python: >=3.5
Requires-Dist: scipy
Requires-Dist: numpy
